too_many_repos/__init__.py
too_many_repos/__main__.py
too_many_repos/too_many_repos.py
too_many_repos-0.0.1.dist-info/WHEEL
too_many_repos-0.0.1.dist-info/METADATA
too_many_repos-0.0.1.dist-info/RECORD
