Metadata-Version: 2.1
Name: too-many-repos
Version: 0.0.1
Summary: 
Author: Gilad Barnea
Author-email: cr-gbarn-herolo@allot.com
Requires-Python: >=3.8,<4.0
Classifier: Programming Language :: Python :: 3
Classifier: Programming Language :: Python :: 3.8
Classifier: Programming Language :: Python :: 3.9
Requires-Dist: click (>=7.0,<8.0)
Requires-Dist: rich (>=9.0,<10.0)
